paddleslim/__init__.py
paddleslim/version.py
paddleslim/analysis/__init__.py
paddleslim/analysis/flops.py
paddleslim/analysis/latency.py
paddleslim/analysis/model_size.py
paddleslim/common/__init__.py
paddleslim/common/cached_reader.py
paddleslim/common/controller.py
paddleslim/common/controller_client.py
paddleslim/common/controller_server.py
paddleslim/common/lock.py
paddleslim/common/log_helper.py
paddleslim/common/sa_controller.py
paddleslim/core/__init__.py
paddleslim/core/graph_wrapper.py
paddleslim/core/registry.py
paddleslim/dist/__init__.py
paddleslim/dist/single_distiller.py
paddleslim/models/__init__.py
paddleslim/models/classification_models.py
paddleslim/models/mobilenet.py
paddleslim/models/mobilenet_v2.py
paddleslim/models/resnet.py
paddleslim/models/util.py
paddleslim/nas/__init__.py
paddleslim/nas/sa_nas.py
paddleslim/nas/one_shot/__init__.py
paddleslim/nas/one_shot/one_shot_nas.py
paddleslim/nas/one_shot/super_mnasnet.py
paddleslim/nas/search_space/__init__.py
paddleslim/nas/search_space/base_layer.py
paddleslim/nas/search_space/combine_search_space.py
paddleslim/nas/search_space/darts_space.py
paddleslim/nas/search_space/inception_block.py
paddleslim/nas/search_space/mobilenet_block.py
paddleslim/nas/search_space/mobilenetv1.py
paddleslim/nas/search_space/mobilenetv2.py
paddleslim/nas/search_space/resnet.py
paddleslim/nas/search_space/resnet_block.py
paddleslim/nas/search_space/search_space_base.py
paddleslim/nas/search_space/search_space_factory.py
paddleslim/nas/search_space/search_space_registry.py
paddleslim/nas/search_space/utils.py
paddleslim/pantheon/__init__.py
paddleslim/pantheon/student.py
paddleslim/pantheon/teacher.py
paddleslim/pantheon/utils.py
paddleslim/prune/__init__.py
paddleslim/prune/auto_pruner.py
paddleslim/prune/prune_io.py
paddleslim/prune/prune_walker.py
paddleslim/prune/pruner.py
paddleslim/prune/sensitive.py
paddleslim/prune/sensitive_pruner.py
paddleslim/quant/__init__.py
paddleslim/quant/quant_embedding.py
whs-0.0.0.dist-info/METADATA
whs-0.0.0.dist-info/WHEEL
whs-0.0.0.dist-info/top_level.txt
whs-0.0.0.dist-info/RECORD
